odoo/addons/pos_receipt_vat_detail/README.rst
odoo/addons/pos_receipt_vat_detail/__init__.py
odoo/addons/pos_receipt_vat_detail/__manifest__.py
odoo/addons/pos_receipt_vat_detail/i18n/fr.po
odoo/addons/pos_receipt_vat_detail/i18n/it.po
odoo/addons/pos_receipt_vat_detail/i18n/pos_receipt_vat_detail.pot
odoo/addons/pos_receipt_vat_detail/readme/CONTRIBUTORS.rst
odoo/addons/pos_receipt_vat_detail/readme/DESCRIPTION.rst
odoo/addons/pos_receipt_vat_detail/static/description/icon.png
odoo/addons/pos_receipt_vat_detail/static/description/index.html
odoo/addons/pos_receipt_vat_detail/static/description/with_module.png
odoo/addons/pos_receipt_vat_detail/static/description/without_module.png
odoo/addons/pos_receipt_vat_detail/static/src/js/models.js
odoo/addons/pos_receipt_vat_detail/static/src/xml/order_receipt.xml
odoo_addon_pos_receipt_vat_detail-16.0.1.0.0.4.dist-info/METADATA
odoo_addon_pos_receipt_vat_detail-16.0.1.0.0.4.dist-info/WHEEL
odoo_addon_pos_receipt_vat_detail-16.0.1.0.0.4.dist-info/top_level.txt
odoo_addon_pos_receipt_vat_detail-16.0.1.0.0.4.dist-info/RECORD
